<?xml version="1.0" encoding="utf-8"?>
<optionset Name="cat_activitycategory" localizedName="ActivityCategory" xmlns:xsi="http://www.w3.org/2001/XMLSchema-instance">
  <OptionSetType>picklist</OptionSetType>
  <IsGlobal>1</IsGlobal>
  <IntroducedVersion>1.1.0.9</IntroducedVersion>
  <IsCustomizable>1</IsCustomizable>
  <displaynames>
    <displayname description="ActivityCategory" languagecode="1033" />
  </displaynames>
  <Descriptions>
    <Description description="" languagecode="1033" />
  </Descriptions>
  <options>
    <option value="809060000">
      <labels>
        <label description="Workback" languagecode="1033" />
      </labels>
    </option>
    <option value="809060001">
      <labels>
        <label description="Run of Show" languagecode="1033" />
      </labels>
    </option>
    <option value="809060002">
      <labels>
        <label description="Other" languagecode="1033" />
      </labels>
    </option>
  </options>
</optionset>